rajan_screener/.gitignore
rajan_screener/Screener.py
rajan_screener/__init__.py
rajan_screener-0.0.0.dist-info/METADATA
rajan_screener-0.0.0.dist-info/WHEEL
rajan_screener-0.0.0.dist-info/licenses/LICENSE
rajan_screener-0.0.0.dist-info/RECORD
